wton/__init__.py
wton/settings.py
wton/config/__init__.py
wton/config/_config.py
wton/config/_exceptions.py
wton/config/_wton.py
wton/config/_provider/__init__.py
wton/config/_provider/_dapp.py
wton/tonclient/__init__.py
wton/tonclient/_exceptions.py
wton/tonclient/_client/__init__.py
wton/tonclient/_client/_base.py
wton/tonclient/_client/_dapp/__init__.py
wton/tonclient/_client/_dapp/_dapp.py
wton/tonclient/_client/_dapp/_queries.py
wton/tonclient/utils/__init__.py
wton/tonclient/utils/_exceptions.py
wton/tonclient/utils/_keystores.py
wton/tonclient/utils/_whitelist.py
wton/tonsdk/__init__.py
wton/tonsdk/_exceptions.py
wton/tonsdk/boc/__init__.py
wton/tonsdk/boc/_bit_string.py
wton/tonsdk/boc/_cell.py
wton/tonsdk/contract/__init__.py
wton/tonsdk/contract/wallet/__init__.py
wton/tonsdk/contract/wallet/_wallet_contract.py
wton/tonsdk/contract/wallet/_wallet_contract_v2.py
wton/tonsdk/contract/wallet/_wallet_contract_v3.py
wton/tonsdk/contract/wallet/_wallet_contract_v4.py
wton/tonsdk/crypto/__init__.py
wton/tonsdk/crypto/_keystore.py
wton/tonsdk/crypto/_mnemonic.py
wton/tonsdk/crypto/_settings.py
wton/tonsdk/crypto/_utils.py
wton/tonsdk/crypto/exceptions.py
wton/tonsdk/crypto/bip39/__init__.py
wton/tonsdk/crypto/bip39/_english.py
wton/tonsdk/provider/__init__.py
wton/tonsdk/provider/_address.py
wton/tonsdk/provider/_exceptions.py
wton/tonsdk/provider/_utils/__init__.py
wton/tonsdk/provider/dapp/__init__.py
wton/tonsdk/provider/dapp/_client.py
wton/tonsdk/utils/__init__.py
wton/tonsdk/utils/_address.py
wton/tonsdk/utils/_currency.py
wton/tonsdk/utils/_exceptions.py
wton/tonsdk/utils/_utils.py
wton/ui/__init__.py
wton/ui/_utils.py
wton/ui/direct_cli/__init__.py
wton/ui/direct_cli/__main__.py
wton/ui/direct_cli/_utils.py
wton/ui/direct_cli/_commands/__init__.py
wton/ui/direct_cli/_commands/_base_cmd.py
wton/ui/direct_cli/_commands/_config_cmd.py
wton/ui/direct_cli/_commands/_contract_cmd.py
wton/ui/direct_cli/_commands/_keystore_cmd.py
wton-0.0.12.dist-info/METADATA
wton-0.0.12.dist-info/WHEEL
wton-0.0.12.dist-info/entry_points.txt
wton-0.0.12.dist-info/top_level.txt
wton-0.0.12.dist-info/RECORD
