Metadata-Version: 2.1
Name: wton
Version: 0.0.12
Summary: Universal TON wallet
Author: tonfactory.org
License: Apache 2.0
Keywords: TON,wallet,TON wallet,blockchain
Classifier: Programming Language :: Python :: 3
Classifier: Environment :: Console
Classifier: Environment :: Other Environment
Classifier: Environment :: Web Environment
Classifier: Intended Audience :: Developers
Classifier: Intended Audience :: Financial and Insurance Industry
Classifier: Intended Audience :: End Users/Desktop
Classifier: License :: OSI Approved :: Apache Software License
Classifier: Natural Language :: English
Classifier: Operating System :: OS Independent
Classifier: Programming Language :: Python
Classifier: Programming Language :: Python :: 3
Classifier: Programming Language :: Python :: 3.7
Classifier: Programming Language :: Python :: 3.8
Classifier: Programming Language :: Python :: 3.9
Classifier: Programming Language :: Python :: 3.10
Classifier: Programming Language :: Python :: 3.11
Classifier: Programming Language :: Python :: 3 :: Only
Classifier: Topic :: Adaptive Technologies
Classifier: Topic :: Office/Business :: Financial
Requires-Python: >=3.6
Requires-Dist: aiohttp (==3.8.1)
Requires-Dist: bitarray (==2.5.1)
Requires-Dist: cffi (==1.15.0)
Requires-Dist: click (==8.1.2)
Requires-Dist: crc32c (==2.2.post0)
Requires-Dist: halo (==0.0.31)
Requires-Dist: inquirer (==2.8.0)
Requires-Dist: numpy (==1.22.3)
Requires-Dist: prettytable (==3.3.0)
Requires-Dist: pycparser (==2.21)
Requires-Dist: pydantic (==1.9.0)
Requires-Dist: pynacl (==1.5.0)
Requires-Dist: pyyaml (==6.0)
Requires-Dist: tvm-valuetypes (==0.0.8)
Requires-Dist: typing-extensions (==4.2.0)
Requires-Dist: gql (==3.3.0)
